[
  {
    "id": "DOGEUSDT_1780089154",
    "symbol": "DOGE/USDT",
    "raw_symbol": "DOGEUSDT",
    "timeframe": "1h",
    "direction": "LONG",
    "state": "READY",
    "state_rank": 2,
    "total_score": 65.22,
    "wyckoff_score": 67.07,
    "accumulation_score": 98.49,
    "volume_score": 26.89,
    "obv_cmf_score": 88.05,
    "liquidity_score": 18.88,
    "risk_penalty": 0.0,
    "entry": 0.10033,
    "entry_zone": "0.099988 ~ 0.100629",
    "stop_loss": 0.096161,
    "take_profit1": 0.108668,
    "take_profit2": 0.112836,
    "be_target": 0.106583,
    "invalidation": 0.096161,
    "breakout_level": 0.1012,
    "sl_pct": -4.16,
    "tp1_pct": 8.31,
    "tp2_pct": 12.47,
    "accum_high": 0.1012,
    "accum_low": 0.09646,
    "accum_bars": 44,
    "range_pct": 4.78,
    "rvol": 0.09,
    "vol_ratio": 0.09,
    "adx": 20.05,
    "cmf": 0.1409,
    "obv_norm": 0.2635,
    "quote_volume": 47690992.92317,
    "price_change_pct_24h": 0.0,
    "comment": "quiet accumulation box is stable, OBV and CMF confirm money flow, late accumulation watch zone",
    "wyckoff_detail": {
      "prior_decline": 0.0,
      "selling_climax": 20.0,
      "automatic_rally": 15.0,
      "secondary_test": 15.0,
      "spring": 0.0,
      "lps": 17.07
    },
    "status": "WATCH",
    "result_price": null,
    "result_pct": null,
    "result_time": null,
    "time": "2026-05-29 21:12 UTC"
  },
  {
    "id": "XRPUSDT_1780089152",
    "symbol": "XRP/USDT",
    "raw_symbol": "XRPUSDT",
    "timeframe": "1h",
    "direction": "LONG",
    "state": "READY",
    "state_rank": 2,
    "total_score": 49.35,
    "wyckoff_score": 33.58,
    "accumulation_score": 69.68,
    "volume_score": 29.91,
    "obv_cmf_score": 78.69,
    "liquidity_score": 40.69,
    "risk_penalty": 0.0,
    "entry": 1.3242,
    "entry_zone": "1.320133 ~ 1.327758",
    "stop_loss": 1.264142,
    "take_profit1": 1.444317,
    "take_profit2": 1.504375,
    "be_target": 1.414287,
    "invalidation": 1.264142,
    "breakout_level": 1.3385,
    "sl_pct": -4.54,
    "tp1_pct": 9.07,
    "tp2_pct": 13.61,
    "accum_high": 1.3385,
    "accum_low": 1.2677,
    "accum_bars": 48,
    "range_pct": 5.41,
    "rvol": 0.07,
    "vol_ratio": 0.07,
    "adx": 15.81,
    "cmf": 0.1025,
    "obv_norm": 0.2436,
    "quote_volume": 130132472.60156,
    "price_change_pct_24h": 0.25,
    "comment": "OBV and CMF confirm money flow, late accumulation watch zone",
    "wyckoff_detail": {
      "prior_decline": 0.0,
      "selling_climax": 0.0,
      "automatic_rally": 9.28,
      "secondary_test": 8.3,
      "spring": 0.0,
      "lps": 16.0
    },
    "status": "WATCH",
    "result_price": null,
    "result_pct": null,
    "result_time": null,
    "time": "2026-05-29 21:12 UTC"
  },
  {
    "id": "ETHUSDT_1780089150",
    "symbol": "ETH/USDT",
    "raw_symbol": "ETHUSDT",
    "timeframe": "1h",
    "direction": "LONG",
    "state": "READY",
    "state_rank": 2,
    "total_score": 40.48,
    "wyckoff_score": 25.71,
    "accumulation_score": 47.36,
    "volume_score": 23.78,
    "obv_cmf_score": 59.22,
    "liquidity_score": 72.85,
    "risk_penalty": 0.0,
    "entry": 2020.42,
    "entry_zone": "2025.979296 ~ 2029.502",
    "stop_loss": 1961.440704,
    "take_profit1": 2138.378592,
    "take_profit2": 2197.357888,
    "be_target": 2108.888944,
    "invalidation": 1961.440704,
    "breakout_level": 2080.64,
    "sl_pct": -2.92,
    "tp1_pct": 5.84,
    "tp2_pct": 8.76,
    "accum_high": 2080.64,
    "accum_low": 1967.0,
    "accum_bars": 56,
    "range_pct": 5.64,
    "rvol": 0.09,
    "vol_ratio": 0.09,
    "adx": 19.45,
    "cmf": 0.1038,
    "obv_norm": 0.1484,
    "quote_volume": 571787358.421881,
    "price_change_pct_24h": 0.1,
    "comment": "late accumulation watch zone",
    "wyckoff_detail": {
      "prior_decline": 0.0,
      "selling_climax": 0.0,
      "automatic_rally": 0.55,
      "secondary_test": 15.0,
      "spring": 0.0,
      "lps": 10.15
    },
    "status": "WATCH",
    "result_price": null,
    "result_pct": null,
    "result_time": null,
    "time": "2026-05-29 21:12 UTC"
  }
]