[
  {
    "id": "DOGEUSDT_1780112961",
    "symbol": "DOGE/USDT",
    "raw_symbol": "DOGEUSDT",
    "timeframe": "1h",
    "direction": "LONG",
    "state": "READY",
    "state_rank": 2,
    "total_score": 66.12,
    "wyckoff_score": 66.44,
    "accumulation_score": 94.75,
    "volume_score": 30.0,
    "obv_cmf_score": 96.63,
    "liquidity_score": 20.05,
    "risk_penalty": 0.0,
    "entry": 0.10129,
    "entry_zone": "0.100962 ~ 0.101102",
    "stop_loss": 0.096173,
    "take_profit1": 0.111524,
    "take_profit2": 0.116641,
    "be_target": 0.108965,
    "invalidation": 0.096173,
    "breakout_level": 0.10161,
    "sl_pct": -5.05,
    "tp1_pct": 10.1,
    "tp2_pct": 15.16,
    "accum_high": 0.10161,
    "accum_low": 0.09646,
    "accum_bars": 48,
    "range_pct": 5.19,
    "rvol": 0.65,
    "vol_ratio": 0.65,
    "adx": 25.22,
    "cmf": 0.2036,
    "obv_norm": 0.2987,
    "quote_volume": 50318041.87047,
    "price_change_pct_24h": 2.11,
    "comment": "quiet accumulation box is stable, OBV and CMF confirm money flow, late accumulation watch zone",
    "wyckoff_detail": {
      "prior_decline": 0.0,
      "selling_climax": 20.0,
      "automatic_rally": 15.0,
      "secondary_test": 12.11,
      "spring": 0.0,
      "lps": 19.33
    },
    "status": "WATCH",
    "result_price": null,
    "result_pct": null,
    "result_time": null,
    "time": "2026-05-30 03:49 UTC"
  },
  {
    "id": "XRPUSDT_1780112958",
    "symbol": "XRP/USDT",
    "raw_symbol": "XRPUSDT",
    "timeframe": "1h",
    "direction": "LONG",
    "state": "READY",
    "state_rank": 2,
    "total_score": 51.22,
    "wyckoff_score": 35.85,
    "accumulation_score": 68.87,
    "volume_score": 35.0,
    "obv_cmf_score": 80.0,
    "liquidity_score": 44.69,
    "risk_penalty": 0.22,
    "entry": 1.3527,
    "entry_zone": "1.347617 ~ 1.357148",
    "stop_loss": 1.263252,
    "take_profit1": 1.531596,
    "take_profit2": 1.621043,
    "be_target": 1.486872,
    "invalidation": 1.263252,
    "breakout_level": 1.3661,
    "sl_pct": -6.61,
    "tp1_pct": 13.23,
    "tp2_pct": 19.84,
    "accum_high": 1.3661,
    "accum_low": 1.2677,
    "accum_bars": 64,
    "range_pct": 7.48,
    "rvol": 1.0,
    "vol_ratio": 1.0,
    "adx": 31.48,
    "cmf": 0.1323,
    "obv_norm": 0.356,
    "quote_volume": 156437364.04475,
    "price_change_pct_24h": 3.06,
    "comment": "OBV and CMF confirm money flow, late accumulation watch zone",
    "wyckoff_detail": {
      "prior_decline": 0.0,
      "selling_climax": 0.0,
      "automatic_rally": 4.57,
      "secondary_test": 15.0,
      "spring": 0.0,
      "lps": 16.27
    },
    "status": "WATCH",
    "result_price": null,
    "result_pct": null,
    "result_time": null,
    "time": "2026-05-30 03:49 UTC"
  },
  {
    "id": "BNBUSDT_1780112959",
    "symbol": "BNB/USDT",
    "raw_symbol": "BNBUSDT",
    "timeframe": "1h",
    "direction": "LONG",
    "state": "TRIGGER",
    "state_rank": 0,
    "total_score": 49.68,
    "wyckoff_score": 30.86,
    "accumulation_score": 40.0,
    "volume_score": 65.01,
    "obv_cmf_score": 72.06,
    "liquidity_score": 36.1,
    "risk_penalty": 0.0,
    "entry": 658.38,
    "entry_zone": "657.104453 ~ 663.1995",
    "stop_loss": 626.731862,
    "take_profit1": 721.676275,
    "take_profit2": 753.324413,
    "be_target": 705.852207,
    "invalidation": 626.731862,
    "breakout_level": 659.9,
    "sl_pct": -4.81,
    "tp1_pct": 9.61,
    "tp2_pct": 14.42,
    "accum_high": 659.9,
    "accum_low": 628.22,
    "accum_bars": 68,
    "range_pct": 4.93,
    "rvol": 2.16,
    "vol_ratio": 2.16,
    "adx": 33.27,
    "cmf": 0.3104,
    "obv_norm": 0.1134,
    "quote_volume": 105368314.48839,
    "price_change_pct_24h": 3.55,
    "comment": "RVOL 2.16x is leading price, OBV and CMF confirm money flow, price is retesting the box ceiling",
    "wyckoff_detail": {
      "prior_decline": 0.0,
      "selling_climax": 0.0,
      "automatic_rally": 0.0,
      "secondary_test": 15.0,
      "spring": 0.0,
      "lps": 15.86
    },
    "status": "WATCH",
    "result_price": null,
    "result_pct": null,
    "result_time": null,
    "time": "2026-05-30 03:49 UTC"
  },
  {
    "id": "LINKUSDT_1780112964",
    "symbol": "LINK/USDT",
    "raw_symbol": "LINKUSDT",
    "timeframe": "1h",
    "direction": "LONG",
    "state": "READY",
    "state_rank": 2,
    "total_score": 48.83,
    "wyckoff_score": 31.21,
    "accumulation_score": 69.37,
    "volume_score": 35.0,
    "obv_cmf_score": 100.0,
    "liquidity_score": 1.25,
    "risk_penalty": 0.0,
    "entry": 9.257,
    "entry_zone": "9.221819 ~ 9.287783",
    "stop_loss": 8.731217,
    "take_profit1": 10.308567,
    "take_profit2": 10.83435,
    "be_target": 10.045675,
    "invalidation": 8.731217,
    "breakout_level": 9.484,
    "sl_pct": -5.68,
    "tp1_pct": 11.36,
    "tp2_pct": 17.04,
    "accum_high": 9.484,
    "accum_low": 8.762,
    "accum_bars": 64,
    "range_pct": 7.98,
    "rvol": 0.99,
    "vol_ratio": 0.99,
    "adx": 28.88,
    "cmf": 0.2424,
    "obv_norm": 0.2547,
    "quote_volume": 21182435.12628,
    "price_change_pct_24h": 3.33,
    "comment": "OBV and CMF confirm money flow, late accumulation watch zone",
    "wyckoff_detail": {
      "prior_decline": 0.0,
      "selling_climax": 0.0,
      "automatic_rally": 0.0,
      "secondary_test": 15.0,
      "spring": 0.0,
      "lps": 16.21
    },
    "status": "WATCH",
    "result_price": null,
    "result_pct": null,
    "result_time": null,
    "time": "2026-05-30 03:49 UTC"
  },
  {
    "id": "ETHUSDT_1780112957",
    "symbol": "ETH/USDT",
    "raw_symbol": "ETHUSDT",
    "timeframe": "1h",
    "direction": "LONG",
    "state": "READY",
    "state_rank": 2,
    "total_score": 47.37,
    "wyckoff_score": 32.43,
    "accumulation_score": 58.57,
    "volume_score": 14.06,
    "obv_cmf_score": 86.52,
    "liquidity_score": 72.04,
    "risk_penalty": 0.0,
    "entry": 2017.35,
    "entry_zone": "2021.422791 ~ 2021.527",
    "stop_loss": 1962.927209,
    "take_profit1": 2126.195583,
    "take_profit2": 2180.618374,
    "be_target": 2098.984187,
    "invalidation": 1962.927209,
    "breakout_level": 2066.14,
    "sl_pct": -2.7,
    "tp1_pct": 5.4,
    "tp2_pct": 8.09,
    "accum_high": 2066.14,
    "accum_low": 1967.0,
    "accum_bars": 56,
    "range_pct": 4.93,
    "rvol": 0.35,
    "vol_ratio": 0.35,
    "adx": 15.68,
    "cmf": 0.1417,
    "obv_norm": 0.2658,
    "quote_volume": 551002294.279966,
    "price_change_pct_24h": 0.7,
    "comment": "OBV and CMF confirm money flow, late accumulation watch zone",
    "wyckoff_detail": {
      "prior_decline": 0.0,
      "selling_climax": 0.0,
      "automatic_rally": 1.73,
      "secondary_test": 15.0,
      "spring": 0.0,
      "lps": 15.7
    },
    "status": "WATCH",
    "result_price": null,
    "result_pct": null,
    "result_time": null,
    "time": "2026-05-30 03:49 UTC"
  },
  {
    "id": "ADAUSDT_1780112963",
    "symbol": "ADA/USDT",
    "raw_symbol": "ADAUSDT",
    "timeframe": "1h",
    "direction": "LONG",
    "state": "READY",
    "state_rank": 2,
    "total_score": 41.84,
    "wyckoff_score": 29.19,
    "accumulation_score": 54.03,
    "volume_score": 70.81,
    "obv_cmf_score": 33.0,
    "liquidity_score": 4.68,
    "risk_penalty": 0.0,
    "entry": 0.2367,
    "entry_zone": "0.236525 ~ 0.237545",
    "stop_loss": 0.227155,
    "take_profit1": 0.25579,
    "take_profit2": 0.265335,
    "be_target": 0.251018,
    "invalidation": 0.227155,
    "breakout_level": 0.2435,
    "sl_pct": -4.03,
    "tp1_pct": 8.07,
    "tp2_pct": 12.1,
    "accum_high": 0.2435,
    "accum_low": 0.228,
    "accum_bars": 64,
    "range_pct": 6.6,
    "rvol": 1.96,
    "vol_ratio": 1.96,
    "adx": 24.18,
    "cmf": 0.1227,
    "obv_norm": -0.0719,
    "quote_volume": 24808766.46171,
    "price_change_pct_24h": 1.41,
    "comment": "RVOL 1.96x is leading price, late accumulation watch zone",
    "wyckoff_detail": {
      "prior_decline": 0.0,
      "selling_climax": 0.0,
      "automatic_rally": 0.0,
      "secondary_test": 15.0,
      "spring": 0.0,
      "lps": 14.19
    },
    "status": "WATCH",
    "result_price": null,
    "result_pct": null,
    "result_time": null,
    "time": "2026-05-30 03:49 UTC"
  }
]