[
  {
    "id": "TRXUSDT_1780251627",
    "symbol": "TRX/USDT",
    "raw_symbol": "TRXUSDT",
    "timeframe": "1h",
    "direction": "LONG",
    "state": "READY",
    "state_rank": 2,
    "total_score": 43.29,
    "wyckoff_score": 62.39,
    "accumulation_score": 47.07,
    "volume_score": 18.84,
    "obv_cmf_score": 53.71,
    "liquidity_score": 9.82,
    "risk_penalty": 0.0,
    "entry": 0.3491,
    "entry_zone": "0.348724 ~ 0.349429",
    "stop_loss": 0.339571,
    "take_profit1": 0.368158,
    "take_profit2": 0.377687,
    "be_target": 0.363393,
    "invalidation": 0.339571,
    "breakout_level": 0.3543,
    "sl_pct": -2.73,
    "tp1_pct": 5.46,
    "tp2_pct": 8.19,
    "accum_high": 0.3543,
    "accum_low": 0.3399,
    "accum_bars": 76,
    "range_pct": 4.15,
    "rvol": 0.31,
    "vol_ratio": 0.31,
    "adx": 33.52,
    "cmf": 0.0529,
    "obv_norm": 0.1886,
    "quote_volume": 31425540.81736,
    "price_change_pct_24h": 0.29,
    "comment": "late accumulation watch zone",
    "wyckoff_detail": {
      "prior_decline": 5.86,
      "selling_climax": 12.16,
      "automatic_rally": 9.58,
      "secondary_test": 15.0,
      "spring": 0.0,
      "lps": 19.79
    },
    "status": "WATCH",
    "result_price": null,
    "result_pct": null,
    "result_time": null,
    "time": "2026-05-31 18:20 UTC"
  },
  {
    "id": "ETHUSDT_1780251622",
    "symbol": "ETH/USDT",
    "raw_symbol": "ETHUSDT",
    "timeframe": "1h",
    "direction": "LONG",
    "state": "READY",
    "state_rank": 2,
    "total_score": 39.27,
    "wyckoff_score": 58.42,
    "accumulation_score": 62.74,
    "volume_score": 2.86,
    "obv_cmf_score": 0.0,
    "liquidity_score": 54.91,
    "risk_penalty": 0.0,
    "entry": 2001.89,
    "entry_zone": "2004.754419 ~ 2010.9455",
    "stop_loss": 1964.515581,
    "take_profit1": 2076.638837,
    "take_profit2": 2114.013256,
    "be_target": 2057.951628,
    "invalidation": 1964.515581,
    "breakout_level": 2046.59,
    "sl_pct": -1.87,
    "tp1_pct": 3.73,
    "tp2_pct": 5.6,
    "accum_high": 2046.59,
    "accum_low": 1967.38,
    "accum_bars": 76,
    "range_pct": 3.93,
    "rvol": 0.28,
    "vol_ratio": 0.28,
    "adx": 50.01,
    "cmf": -0.1039,
    "obv_norm": -0.2339,
    "quote_volume": 250425118.13066,
    "price_change_pct_24h": -1.31,
    "comment": "late accumulation watch zone",
    "wyckoff_detail": {
      "prior_decline": 6.49,
      "selling_climax": 10.23,
      "automatic_rally": 15.0,
      "secondary_test": 15.0,
      "spring": 0.0,
      "lps": 11.7
    },
    "status": "WATCH",
    "result_price": null,
    "result_pct": null,
    "result_time": null,
    "time": "2026-05-31 18:20 UTC"
  }
]