[
  {
    "id": "DOGEUSDT_1780095390",
    "symbol": "DOGE/USDT",
    "raw_symbol": "DOGEUSDT",
    "timeframe": "1h",
    "direction": "LONG",
    "state": "READY",
    "state_rank": 2,
    "total_score": 62.64,
    "wyckoff_score": 63.55,
    "accumulation_score": 100.0,
    "volume_score": 15.83,
    "obv_cmf_score": 90.24,
    "liquidity_score": 18.71,
    "risk_penalty": 0.0,
    "entry": 0.09986,
    "entry_zone": "0.099503 ~ 0.100173",
    "stop_loss": 0.096147,
    "take_profit1": 0.107285,
    "take_profit2": 0.110998,
    "be_target": 0.105429,
    "invalidation": 0.096147,
    "breakout_level": 0.1012,
    "sl_pct": -3.72,
    "tp1_pct": 7.44,
    "tp2_pct": 11.15,
    "accum_high": 0.1012,
    "accum_low": 0.09646,
    "accum_bars": 44,
    "range_pct": 4.78,
    "rvol": 0.27,
    "vol_ratio": 0.27,
    "adx": 22.15,
    "cmf": 0.1387,
    "obv_norm": 0.2603,
    "quote_volume": 47310542.33213,
    "price_change_pct_24h": 0.28,
    "comment": "quiet accumulation box is stable, OBV and CMF confirm money flow, late accumulation watch zone",
    "wyckoff_detail": {
      "prior_decline": 0.0,
      "selling_climax": 20.0,
      "automatic_rally": 15.0,
      "secondary_test": 12.11,
      "spring": 0.0,
      "lps": 16.44
    },
    "status": "WATCH",
    "result_price": null,
    "result_pct": null,
    "result_time": null,
    "time": "2026-05-29 22:56 UTC"
  },
  {
    "id": "XRPUSDT_1780095387",
    "symbol": "XRP/USDT",
    "raw_symbol": "XRPUSDT",
    "timeframe": "1h",
    "direction": "LONG",
    "state": "READY",
    "state_rank": 2,
    "total_score": 51.31,
    "wyckoff_score": 40.28,
    "accumulation_score": 69.36,
    "volume_score": 17.3,
    "obv_cmf_score": 95.7,
    "liquidity_score": 40.75,
    "risk_penalty": 0.0,
    "entry": 1.3204,
    "entry_zone": "1.31611 ~ 1.324154",
    "stop_loss": 1.263946,
    "take_profit1": 1.433307,
    "take_profit2": 1.489761,
    "be_target": 1.40508,
    "invalidation": 1.263946,
    "breakout_level": 1.3385,
    "sl_pct": -4.28,
    "tp1_pct": 8.55,
    "tp2_pct": 12.83,
    "accum_high": 1.3385,
    "accum_low": 1.2677,
    "accum_bars": 52,
    "range_pct": 5.4,
    "rvol": 0.51,
    "vol_ratio": 0.51,
    "adx": 17.27,
    "cmf": 0.1198,
    "obv_norm": 0.2484,
    "quote_volume": 130486009.94259,
    "price_change_pct_24h": 0.39,
    "comment": "OBV and CMF confirm money flow, late accumulation watch zone",
    "wyckoff_detail": {
      "prior_decline": 0.0,
      "selling_climax": 0.0,
      "automatic_rally": 9.28,
      "secondary_test": 15.0,
      "spring": 0.0,
      "lps": 16.0
    },
    "status": "WATCH",
    "result_price": null,
    "result_pct": null,
    "result_time": null,
    "time": "2026-05-29 22:56 UTC"
  },
  {
    "id": "ETHUSDT_1780095386",
    "symbol": "ETH/USDT",
    "raw_symbol": "ETHUSDT",
    "timeframe": "1h",
    "direction": "LONG",
    "state": "READY",
    "state_rank": 2,
    "total_score": 41.37,
    "wyckoff_score": 35.13,
    "accumulation_score": 48.66,
    "volume_score": 11.84,
    "obv_cmf_score": 60.22,
    "liquidity_score": 72.64,
    "risk_penalty": 0.0,
    "entry": 2013.82,
    "entry_zone": "2010.7745 ~ 2019.590741",
    "stop_loss": 1961.229259,
    "take_profit1": 2119.001482,
    "take_profit2": 2171.592223,
    "be_target": 2092.706111,
    "invalidation": 1961.229259,
    "breakout_level": 2046.59,
    "sl_pct": -2.61,
    "tp1_pct": 5.22,
    "tp2_pct": 7.83,
    "accum_high": 2046.59,
    "accum_low": 1967.0,
    "accum_bars": 48,
    "range_pct": 3.97,
    "rvol": 0.62,
    "vol_ratio": 0.62,
    "adx": 20.82,
    "cmf": 0.1087,
    "obv_norm": 0.1533,
    "quote_volume": 566311508.305749,
    "price_change_pct_24h": 0.3,
    "comment": "OBV and CMF confirm money flow, late accumulation watch zone",
    "wyckoff_detail": {
      "prior_decline": 0.68,
      "selling_climax": 0.0,
      "automatic_rally": 4.0,
      "secondary_test": 15.0,
      "spring": 0.0,
      "lps": 15.45
    },
    "status": "WATCH",
    "result_price": null,
    "result_pct": null,
    "result_time": null,
    "time": "2026-05-29 22:56 UTC"
  }
]