[
  {
    "id": "TRXUSDT_1780268820",
    "symbol": "TRX/USDT",
    "raw_symbol": "TRXUSDT",
    "timeframe": "1h",
    "direction": "LONG",
    "state": "READY",
    "state_rank": 2,
    "total_score": 53.27,
    "wyckoff_score": 60.92,
    "accumulation_score": 51.95,
    "volume_score": 30.0,
    "obv_cmf_score": 100.0,
    "liquidity_score": 10.09,
    "risk_penalty": 0.0,
    "entry": 0.3509,
    "entry_zone": "0.350574 ~ 0.351185",
    "stop_loss": 0.339615,
    "take_profit1": 0.373471,
    "take_profit2": 0.384756,
    "be_target": 0.367828,
    "invalidation": 0.339615,
    "breakout_level": 0.3543,
    "sl_pct": -3.22,
    "tp1_pct": 6.43,
    "tp2_pct": 9.65,
    "accum_high": 0.3543,
    "accum_low": 0.3399,
    "accum_bars": 80,
    "range_pct": 4.14,
    "rvol": 0.03,
    "vol_ratio": 0.03,
    "adx": 46.32,
    "cmf": 0.1892,
    "obv_norm": 0.4147,
    "quote_volume": 31821585.48908,
    "price_change_pct_24h": 0.95,
    "comment": "OBV and CMF confirm money flow, late accumulation watch zone",
    "wyckoff_detail": {
      "prior_decline": 4.17,
      "selling_climax": 12.16,
      "automatic_rally": 9.58,
      "secondary_test": 15.0,
      "spring": 0.0,
      "lps": 20.0
    },
    "status": "WATCH",
    "result_price": null,
    "result_pct": null,
    "result_time": null,
    "time": "2026-05-31 23:07 UTC"
  },
  {
    "id": "ETHUSDT_1780268815",
    "symbol": "ETH/USDT",
    "raw_symbol": "ETHUSDT",
    "timeframe": "1h",
    "direction": "LONG",
    "state": "READY",
    "state_rank": 2,
    "total_score": 42.94,
    "wyckoff_score": 47.72,
    "accumulation_score": 69.03,
    "volume_score": 7.91,
    "obv_cmf_score": 25.48,
    "liquidity_score": 59.61,
    "risk_penalty": 0.0,
    "entry": 2017.65,
    "entry_zone": "2015.0405 ~ 2020.82502",
    "stop_loss": 1973.30498,
    "take_profit1": 2106.34004,
    "take_profit2": 2150.68506,
    "be_target": 2084.16753,
    "invalidation": 1973.30498,
    "breakout_level": 2046.59,
    "sl_pct": -2.2,
    "tp1_pct": 4.4,
    "tp2_pct": 6.59,
    "accum_high": 2046.59,
    "accum_low": 1976.48,
    "accum_bars": 80,
    "range_pct": 3.48,
    "rvol": 0.31,
    "vol_ratio": 0.31,
    "adx": 39.74,
    "cmf": 0.057,
    "obv_norm": -0.2414,
    "quote_volume": 310896878.37748,
    "price_change_pct_24h": -0.37,
    "comment": "late accumulation watch zone",
    "wyckoff_detail": {
      "prior_decline": 5.46,
      "selling_climax": 0.0,
      "automatic_rally": 11.69,
      "secondary_test": 15.0,
      "spring": 0.0,
      "lps": 15.58
    },
    "status": "WATCH",
    "result_price": null,
    "result_pct": null,
    "result_time": null,
    "time": "2026-05-31 23:06 UTC"
  }
]