[
  {
    "id": "DOGEUSDT_1780102530",
    "symbol": "DOGE/USDT",
    "raw_symbol": "DOGEUSDT",
    "timeframe": "1h",
    "direction": "LONG",
    "state": "READY",
    "state_rank": 2,
    "total_score": 64.57,
    "wyckoff_score": 65.3,
    "accumulation_score": 100.0,
    "volume_score": 22.06,
    "obv_cmf_score": 91.18,
    "liquidity_score": 18.93,
    "risk_penalty": 0.0,
    "entry": 0.10014,
    "entry_zone": "0.099809 ~ 0.10043",
    "stop_loss": 0.09617,
    "take_profit1": 0.108079,
    "take_profit2": 0.112049,
    "be_target": 0.106095,
    "invalidation": 0.09617,
    "breakout_level": 0.1012,
    "sl_pct": -3.96,
    "tp1_pct": 7.93,
    "tp2_pct": 11.89,
    "accum_high": 0.1012,
    "accum_low": 0.09646,
    "accum_bars": 44,
    "range_pct": 4.78,
    "rvol": 0.35,
    "vol_ratio": 0.35,
    "adx": 21.45,
    "cmf": 0.1592,
    "obv_norm": 0.2842,
    "quote_volume": 47805755.24602,
    "price_change_pct_24h": 0.33,
    "comment": "quiet accumulation box is stable, OBV and CMF confirm money flow, late accumulation watch zone",
    "wyckoff_detail": {
      "prior_decline": 2.07,
      "selling_climax": 20.0,
      "automatic_rally": 15.0,
      "secondary_test": 12.11,
      "spring": 0.0,
      "lps": 16.12
    },
    "status": "WATCH",
    "result_price": null,
    "result_pct": null,
    "result_time": null,
    "time": "2026-05-30 00:55 UTC"
  },
  {
    "id": "XRPUSDT_1780102527",
    "symbol": "XRP/USDT",
    "raw_symbol": "XRPUSDT",
    "timeframe": "1h",
    "direction": "LONG",
    "state": "TRIGGER",
    "state_rank": 0,
    "total_score": 62.57,
    "wyckoff_score": 36.28,
    "accumulation_score": 70.0,
    "volume_score": 60.0,
    "obv_cmf_score": 100.0,
    "liquidity_score": 41.85,
    "risk_penalty": 0.0,
    "entry": 1.343,
    "entry_zone": "1.33958 ~ 1.350418",
    "stop_loss": 1.26371,
    "take_profit1": 1.501581,
    "take_profit2": 1.580871,
    "be_target": 1.461936,
    "invalidation": 1.26371,
    "breakout_level": 1.3437,
    "sl_pct": -5.9,
    "tp1_pct": 11.81,
    "tp2_pct": 17.71,
    "accum_high": 1.3437,
    "accum_low": 1.2677,
    "accum_bars": 60,
    "range_pct": 5.79,
    "rvol": 1.56,
    "vol_ratio": 1.56,
    "adx": 18.8,
    "cmf": 0.1704,
    "obv_norm": 0.2848,
    "quote_volume": 137278028.51637,
    "price_change_pct_24h": 2.16,
    "comment": "quiet accumulation box is stable, OBV and CMF confirm money flow, price is retesting the box ceiling",
    "wyckoff_detail": {
      "prior_decline": 0.0,
      "selling_climax": 0.0,
      "automatic_rally": 8.13,
      "secondary_test": 15.0,
      "spring": 0.0,
      "lps": 13.14
    },
    "status": "WATCH",
    "result_price": null,
    "result_pct": null,
    "result_time": null,
    "time": "2026-05-30 00:55 UTC"
  },
  {
    "id": "ETHUSDT_1780102526",
    "symbol": "ETH/USDT",
    "raw_symbol": "ETHUSDT",
    "timeframe": "1h",
    "direction": "LONG",
    "state": "READY",
    "state_rank": 2,
    "total_score": 42.64,
    "wyckoff_score": 27.44,
    "accumulation_score": 52.03,
    "volume_score": 11.55,
    "obv_cmf_score": 78.88,
    "liquidity_score": 72.56,
    "risk_penalty": 0.0,
    "entry": 2015.25,
    "entry_zone": "2020.18849 ~ 2021.527",
    "stop_loss": 1962.06151,
    "take_profit1": 2121.62698,
    "take_profit2": 2174.815469,
    "be_target": 2095.032735,
    "invalidation": 1962.06151,
    "breakout_level": 2066.14,
    "sl_pct": -2.64,
    "tp1_pct": 5.28,
    "tp2_pct": 7.92,
    "accum_high": 2066.14,
    "accum_low": 1967.0,
    "accum_bars": 52,
    "range_pct": 4.94,
    "rvol": 0.25,
    "vol_ratio": 0.25,
    "adx": 20.8,
    "cmf": 0.1215,
    "obv_norm": 0.2073,
    "quote_volume": 564374514.338388,
    "price_change_pct_24h": 0.17,
    "comment": "OBV and CMF confirm money flow, late accumulation watch zone",
    "wyckoff_detail": {
      "prior_decline": 0.0,
      "selling_climax": 0.0,
      "automatic_rally": 1.73,
      "secondary_test": 15.0,
      "spring": 0.0,
      "lps": 10.71
    },
    "status": "WATCH",
    "result_price": null,
    "result_pct": null,
    "result_time": null,
    "time": "2026-05-30 00:55 UTC"
  },
  {
    "id": "BNBUSDT_1780102528",
    "symbol": "BNB/USDT",
    "raw_symbol": "BNBUSDT",
    "timeframe": "1h",
    "direction": "LONG",
    "state": "READY",
    "state_rank": 2,
    "total_score": 38.05,
    "wyckoff_score": 30.81,
    "accumulation_score": 37.12,
    "volume_score": 58.2,
    "obv_cmf_score": 33.0,
    "liquidity_score": 29.38,
    "risk_penalty": 0.0,
    "entry": 647.1,
    "entry_zone": "645.744803 ~ 648.285797",
    "stop_loss": 627.034203,
    "take_profit1": 687.231595,
    "take_profit2": 707.297392,
    "be_target": 677.198696,
    "invalidation": 627.034203,
    "breakout_level": 659.9,
    "sl_pct": -3.1,
    "tp1_pct": 6.2,
    "tp2_pct": 9.3,
    "accum_high": 659.9,
    "accum_low": 628.22,
    "accum_bars": 60,
    "range_pct": 4.94,
    "rvol": 1.6,
    "vol_ratio": 1.6,
    "adx": 14.71,
    "cmf": 0.1726,
    "obv_norm": -0.1349,
    "quote_volume": 77340131.44136,
    "price_change_pct_24h": 1.36,
    "comment": "late accumulation watch zone",
    "wyckoff_detail": {
      "prior_decline": 0.0,
      "selling_climax": 0.0,
      "automatic_rally": 0.0,
      "secondary_test": 15.0,
      "spring": 0.0,
      "lps": 15.81
    },
    "status": "WATCH",
    "result_price": null,
    "result_pct": null,
    "result_time": null,
    "time": "2026-05-30 00:55 UTC"
  }
]