[
  {
    "id": "DOGEUSDT_1780132474",
    "symbol": "DOGE/USDT",
    "raw_symbol": "DOGEUSDT",
    "timeframe": "1h",
    "direction": "LONG",
    "state": "READY",
    "state_rank": 2,
    "total_score": 64.97,
    "wyckoff_score": 66.01,
    "accumulation_score": 99.72,
    "volume_score": 30.0,
    "obv_cmf_score": 80.27,
    "liquidity_score": 21.94,
    "risk_penalty": 0.0,
    "entry": 0.10099,
    "entry_zone": "0.100723 ~ 0.101223",
    "stop_loss": 0.096227,
    "take_profit1": 0.110516,
    "take_profit2": 0.11528,
    "be_target": 0.108135,
    "invalidation": 0.096227,
    "breakout_level": 0.10213,
    "sl_pct": -4.72,
    "tp1_pct": 9.43,
    "tp2_pct": 14.15,
    "accum_high": 0.10213,
    "accum_low": 0.09646,
    "accum_bars": 60,
    "range_pct": 5.69,
    "rvol": 0.09,
    "vol_ratio": 0.09,
    "adx": 14.92,
    "cmf": 0.2245,
    "obv_norm": 0.1977,
    "quote_volume": 54893055.50166,
    "price_change_pct_24h": 1.3,
    "comment": "quiet accumulation box is stable, OBV and CMF confirm money flow, late accumulation watch zone",
    "wyckoff_detail": {
      "prior_decline": 0.0,
      "selling_climax": 20.0,
      "automatic_rally": 14.03,
      "secondary_test": 12.11,
      "spring": 0.0,
      "lps": 19.87
    },
    "status": "WATCH",
    "result_price": null,
    "result_pct": null,
    "result_time": null,
    "time": "2026-05-30 09:14 UTC"
  },
  {
    "id": "XRPUSDT_1780132471",
    "symbol": "XRP/USDT",
    "raw_symbol": "XRPUSDT",
    "timeframe": "1h",
    "direction": "LONG",
    "state": "READY",
    "state_rank": 2,
    "total_score": 50.37,
    "wyckoff_score": 33.01,
    "accumulation_score": 60.0,
    "volume_score": 30.0,
    "obv_cmf_score": 100.0,
    "liquidity_score": 44.68,
    "risk_penalty": 0.0,
    "entry": 1.3431,
    "entry_zone": "1.339489 ~ 1.346259",
    "stop_loss": 1.291541,
    "take_profit1": 1.446219,
    "take_profit2": 1.497778,
    "be_target": 1.420439,
    "invalidation": 1.291541,
    "breakout_level": 1.3661,
    "sl_pct": -3.84,
    "tp1_pct": 7.68,
    "tp2_pct": 11.52,
    "accum_high": 1.3661,
    "accum_low": 1.2947,
    "accum_bars": 28,
    "range_pct": 5.38,
    "rvol": 0.18,
    "vol_ratio": 0.18,
    "adx": 16.11,
    "cmf": 0.1779,
    "obv_norm": 0.3757,
    "quote_volume": 156356392.68624,
    "price_change_pct_24h": 1.69,
    "comment": "OBV and CMF confirm money flow, late accumulation watch zone",
    "wyckoff_detail": {
      "prior_decline": 0.0,
      "selling_climax": 0.0,
      "automatic_rally": 15.0,
      "secondary_test": 0.0,
      "spring": 0.0,
      "lps": 18.01
    },
    "status": "WATCH",
    "result_price": null,
    "result_pct": null,
    "result_time": null,
    "time": "2026-05-30 09:14 UTC"
  },
  {
    "id": "ETHUSDT_1780132470",
    "symbol": "ETH/USDT",
    "raw_symbol": "ETHUSDT",
    "timeframe": "1h",
    "direction": "LONG",
    "state": "READY",
    "state_rank": 2,
    "total_score": 49.0,
    "wyckoff_score": 30.66,
    "accumulation_score": 72.48,
    "volume_score": 11.75,
    "obv_cmf_score": 82.16,
    "liquidity_score": 70.08,
    "risk_penalty": 0.0,
    "entry": 2015.83,
    "entry_zone": "2015.0405 ~ 2018.809186",
    "stop_loss": 1973.500814,
    "take_profit1": 2100.488372,
    "take_profit2": 2142.817558,
    "be_target": 2079.323779,
    "invalidation": 1973.500814,
    "breakout_level": 2046.59,
    "sl_pct": -2.1,
    "tp1_pct": 4.2,
    "tp2_pct": 6.3,
    "accum_high": 2046.59,
    "accum_low": 1976.48,
    "accum_bars": 32,
    "range_pct": 3.48,
    "rvol": 0.04,
    "vol_ratio": 0.04,
    "adx": 25.08,
    "cmf": 0.2042,
    "obv_norm": 0.3078,
    "quote_volume": 503313003.261852,
    "price_change_pct_24h": 0.14,
    "comment": "quiet accumulation box is stable, OBV and CMF confirm money flow, late accumulation watch zone",
    "wyckoff_detail": {
      "prior_decline": 1.52,
      "selling_climax": 0.0,
      "automatic_rally": 10.96,
      "secondary_test": 0.0,
      "spring": 0.0,
      "lps": 18.19
    },
    "status": "WATCH",
    "result_price": null,
    "result_pct": null,
    "result_time": null,
    "time": "2026-05-30 09:14 UTC"
  },
  {
    "id": "BNBUSDT_1780132472",
    "symbol": "BNB/USDT",
    "raw_symbol": "BNBUSDT",
    "timeframe": "1h",
    "direction": "LONG",
    "state": "READY",
    "state_rank": 2,
    "total_score": 47.51,
    "wyckoff_score": 16.74,
    "accumulation_score": 57.02,
    "volume_score": 45.0,
    "obv_cmf_score": 100.0,
    "liquidity_score": 42.29,
    "risk_penalty": 0.0,
    "entry": 671.4,
    "entry_zone": "669.476678 ~ 672.09265",
    "stop_loss": 629.177094,
    "take_profit1": 755.845813,
    "take_profit2": 798.068719,
    "be_target": 734.73436,
    "invalidation": 629.177094,
    "breakout_level": 675.47,
    "sl_pct": -6.29,
    "tp1_pct": 12.58,
    "tp2_pct": 18.87,
    "accum_high": 675.47,
    "accum_low": 630.86,
    "accum_bars": 28,
    "range_pct": 6.9,
    "rvol": 0.42,
    "vol_ratio": 0.42,
    "adx": 61.06,
    "cmf": 0.4061,
    "obv_norm": 0.6812,
    "quote_volume": 140076004.26577,
    "price_change_pct_24h": 5.15,
    "comment": "OBV and CMF confirm money flow, late accumulation watch zone",
    "wyckoff_detail": {
      "prior_decline": 0.74,
      "selling_climax": 0.0,
      "automatic_rally": 0.0,
      "secondary_test": 0.0,
      "spring": 0.0,
      "lps": 16.0
    },
    "status": "WATCH",
    "result_price": null,
    "result_pct": null,
    "result_time": null,
    "time": "2026-05-30 09:14 UTC"
  },
  {
    "id": "LINKUSDT_1780132477",
    "symbol": "LINK/USDT",
    "raw_symbol": "LINKUSDT",
    "timeframe": "1h",
    "direction": "LONG",
    "state": "READY",
    "state_rank": 2,
    "total_score": 44.89,
    "wyckoff_score": 28.09,
    "accumulation_score": 69.24,
    "volume_score": 25.74,
    "obv_cmf_score": 91.25,
    "liquidity_score": 3.2,
    "risk_penalty": 0.0,
    "entry": 9.139,
    "entry_zone": "9.1591 ~ 9.164482",
    "stop_loss": 8.736518,
    "take_profit1": 9.943964,
    "take_profit2": 10.346446,
    "be_target": 9.742723,
    "invalidation": 8.736518,
    "breakout_level": 9.484,
    "sl_pct": -4.4,
    "tp1_pct": 8.81,
    "tp2_pct": 13.21,
    "accum_high": 9.484,
    "accum_low": 8.762,
    "accum_bars": 72,
    "range_pct": 7.96,
    "rvol": 0.08,
    "vol_ratio": 0.08,
    "adx": 15.66,
    "cmf": 0.2311,
    "obv_norm": 0.2569,
    "quote_volume": 23178546.69186,
    "price_change_pct_24h": 1.19,
    "comment": "OBV and CMF confirm money flow, late accumulation watch zone",
    "wyckoff_detail": {
      "prior_decline": 0.0,
      "selling_climax": 0.0,
      "automatic_rally": 0.0,
      "secondary_test": 15.0,
      "spring": 0.0,
      "lps": 13.09
    },
    "status": "WATCH",
    "result_price": null,
    "result_pct": null,
    "result_time": null,
    "time": "2026-05-30 09:14 UTC"
  }
]