[
  {
    "id": "XRPUSDT_1780128383",
    "symbol": "XRP/USDT",
    "raw_symbol": "XRPUSDT",
    "timeframe": "1h",
    "direction": "LONG",
    "state": "READY",
    "state_rank": 2,
    "total_score": 58.03,
    "wyckoff_score": 58.16,
    "accumulation_score": 60.0,
    "volume_score": 35.0,
    "obv_cmf_score": 93.73,
    "liquidity_score": 45.19,
    "risk_penalty": 0.0,
    "entry": 1.3417,
    "entry_zone": "1.337807 ~ 1.345106",
    "stop_loss": 1.291294,
    "take_profit1": 1.442512,
    "take_profit2": 1.492919,
    "be_target": 1.417309,
    "invalidation": 1.291294,
    "breakout_level": 1.3661,
    "sl_pct": -3.76,
    "tp1_pct": 7.51,
    "tp2_pct": 11.27,
    "accum_high": 1.3661,
    "accum_low": 1.2947,
    "accum_bars": 24,
    "range_pct": 5.37,
    "rvol": 0.02,
    "vol_ratio": 0.02,
    "adx": 18.55,
    "cmf": 0.1792,
    "obv_norm": 0.3639,
    "quote_volume": 160060003.52277,
    "price_change_pct_24h": 1.75,
    "comment": "OBV and CMF confirm money flow, late accumulation watch zone",
    "wyckoff_detail": {
      "prior_decline": 0.0,
      "selling_climax": 9.67,
      "automatic_rally": 15.0,
      "secondary_test": 15.0,
      "spring": 0.0,
      "lps": 18.49
    },
    "status": "WATCH",
    "result_price": null,
    "result_pct": null,
    "result_time": null,
    "time": "2026-05-30 08:06 UTC"
  },
  {
    "id": "DOGEUSDT_1780128386",
    "symbol": "DOGE/USDT",
    "raw_symbol": "DOGEUSDT",
    "timeframe": "1h",
    "direction": "LONG",
    "state": "READY",
    "state_rank": 2,
    "total_score": 55.85,
    "wyckoff_score": 34.25,
    "accumulation_score": 96.1,
    "volume_score": 30.0,
    "obv_cmf_score": 89.1,
    "liquidity_score": 21.88,
    "risk_penalty": 0.0,
    "entry": 0.10125,
    "entry_zone": "0.100982 ~ 0.101484",
    "stop_loss": 0.096226,
    "take_profit1": 0.111298,
    "take_profit2": 0.116322,
    "be_target": 0.108786,
    "invalidation": 0.096226,
    "breakout_level": 0.10339,
    "sl_pct": -4.96,
    "tp1_pct": 9.92,
    "tp2_pct": 14.89,
    "accum_high": 0.10339,
    "accum_low": 0.09646,
    "accum_bars": 68,
    "range_pct": 6.94,
    "rvol": 0.01,
    "vol_ratio": 0.01,
    "adx": 17.66,
    "cmf": 0.2316,
    "obv_norm": 0.2207,
    "quote_volume": 54743990.52711,
    "price_change_pct_24h": 1.65,
    "comment": "quiet accumulation box is stable, OBV and CMF confirm money flow, late accumulation watch zone",
    "wyckoff_detail": {
      "prior_decline": 0.0,
      "selling_climax": 0.0,
      "automatic_rally": 0.0,
      "secondary_test": 14.49,
      "spring": 0.0,
      "lps": 19.76
    },
    "status": "WATCH",
    "result_price": null,
    "result_pct": null,
    "result_time": null,
    "time": "2026-05-30 08:06 UTC"
  },
  {
    "id": "ETHUSDT_1780128382",
    "symbol": "ETH/USDT",
    "raw_symbol": "ETHUSDT",
    "timeframe": "1h",
    "direction": "LONG",
    "state": "READY",
    "state_rank": 2,
    "total_score": 49.85,
    "wyckoff_score": 30.66,
    "accumulation_score": 69.56,
    "volume_score": 6.99,
    "obv_cmf_score": 98.38,
    "liquidity_score": 71.03,
    "risk_penalty": 0.0,
    "entry": 2015.13,
    "entry_zone": "2015.0405 ~ 2018.401138",
    "stop_loss": 1973.208862,
    "take_profit1": 2098.972276,
    "take_profit2": 2140.893414,
    "be_target": 2078.011707,
    "invalidation": 1973.208862,
    "breakout_level": 2046.59,
    "sl_pct": -2.08,
    "tp1_pct": 4.16,
    "tp2_pct": 6.24,
    "accum_high": 2046.59,
    "accum_low": 1976.48,
    "accum_bars": 32,
    "range_pct": 3.48,
    "rvol": 0.01,
    "vol_ratio": 0.01,
    "adx": 24.26,
    "cmf": 0.2124,
    "obv_norm": 0.3184,
    "quote_volume": 526001880.19958,
    "price_change_pct_24h": 0.35,
    "comment": "OBV and CMF confirm money flow, late accumulation watch zone",
    "wyckoff_detail": {
      "prior_decline": 1.98,
      "selling_climax": 0.0,
      "automatic_rally": 10.96,
      "secondary_test": 0.0,
      "spring": 0.0,
      "lps": 17.73
    },
    "status": "WATCH",
    "result_price": null,
    "result_pct": null,
    "result_time": null,
    "time": "2026-05-30 08:06 UTC"
  },
  {
    "id": "BNBUSDT_1780128383",
    "symbol": "BNB/USDT",
    "raw_symbol": "BNBUSDT",
    "timeframe": "1h",
    "direction": "LONG",
    "state": "READY",
    "state_rank": 2,
    "total_score": 47.0,
    "wyckoff_score": 16.2,
    "accumulation_score": 56.09,
    "volume_score": 45.0,
    "obv_cmf_score": 100.0,
    "liquidity_score": 41.16,
    "risk_penalty": 0.0,
    "entry": 672.5,
    "entry_zone": "670.699162 ~ 670.87875",
    "stop_loss": 629.284267,
    "take_profit1": 758.931466,
    "take_profit2": 802.147199,
    "be_target": 737.3236,
    "invalidation": 629.284267,
    "breakout_level": 674.25,
    "sl_pct": -6.43,
    "tp1_pct": 12.85,
    "tp2_pct": 19.28,
    "accum_high": 674.25,
    "accum_low": 630.86,
    "accum_bars": 28,
    "range_pct": 6.72,
    "rvol": 0.23,
    "vol_ratio": 0.23,
    "adx": 57.18,
    "cmf": 0.4073,
    "obv_norm": 0.5905,
    "quote_volume": 132980417.36923,
    "price_change_pct_24h": 5.58,
    "comment": "OBV and CMF confirm money flow, late accumulation watch zone",
    "wyckoff_detail": {
      "prior_decline": 0.87,
      "selling_climax": 0.0,
      "automatic_rally": 0.0,
      "secondary_test": 0.0,
      "spring": 0.0,
      "lps": 15.32
    },
    "status": "WATCH",
    "result_price": null,
    "result_pct": null,
    "result_time": null,
    "time": "2026-05-30 08:06 UTC"
  },
  {
    "id": "LINKUSDT_1780128388",
    "symbol": "LINK/USDT",
    "raw_symbol": "LINKUSDT",
    "timeframe": "1h",
    "direction": "LONG",
    "state": "READY",
    "state_rank": 2,
    "total_score": 43.82,
    "wyckoff_score": 29.29,
    "accumulation_score": 67.99,
    "volume_score": 26.57,
    "obv_cmf_score": 82.6,
    "liquidity_score": 3.36,
    "risk_penalty": 0.0,
    "entry": 9.157,
    "entry_zone": "9.1591 ~ 9.183448",
    "stop_loss": 8.735552,
    "take_profit1": 9.999896,
    "take_profit2": 10.421344,
    "be_target": 9.789172,
    "invalidation": 8.735552,
    "breakout_level": 9.484,
    "sl_pct": -4.6,
    "tp1_pct": 9.2,
    "tp2_pct": 13.81,
    "accum_high": 9.484,
    "accum_low": 8.762,
    "accum_bars": 68,
    "range_pct": 7.97,
    "rvol": 0.05,
    "vol_ratio": 0.05,
    "adx": 18.74,
    "cmf": 0.2402,
    "obv_norm": 0.2592,
    "quote_volume": 23341602.98207,
    "price_change_pct_24h": 1.6,
    "comment": "OBV and CMF confirm money flow, late accumulation watch zone",
    "wyckoff_detail": {
      "prior_decline": 0.0,
      "selling_climax": 0.0,
      "automatic_rally": 0.0,
      "secondary_test": 15.0,
      "spring": 0.0,
      "lps": 14.29
    },
    "status": "WATCH",
    "result_price": null,
    "result_pct": null,
    "result_time": null,
    "time": "2026-05-30 08:06 UTC"
  }
]