[
  {
    "id": "ETHUSDT_1780164198",
    "symbol": "ETH/USDT",
    "raw_symbol": "ETHUSDT",
    "timeframe": "1h",
    "direction": "LONG",
    "state": "READY",
    "state_rank": 2,
    "total_score": 64.04,
    "wyckoff_score": 66.43,
    "accumulation_score": 77.82,
    "volume_score": 19.9,
    "obv_cmf_score": 100.0,
    "liquidity_score": 56.74,
    "risk_penalty": 0.0,
    "entry": 2026.94,
    "entry_zone": "2024.381051 ~ 2029.17908",
    "stop_loss": 1965.14092,
    "take_profit1": 2150.53816,
    "take_profit2": 2212.33724,
    "be_target": 2119.63862,
    "invalidation": 1965.14092,
    "breakout_level": 2046.59,
    "sl_pct": -3.05,
    "tp1_pct": 6.1,
    "tp2_pct": 9.15,
    "accum_high": 2046.59,
    "accum_low": 1967.38,
    "accum_bars": 52,
    "range_pct": 3.93,
    "rvol": 0.04,
    "vol_ratio": 0.04,
    "adx": 22.47,
    "cmf": 0.2162,
    "obv_norm": 0.4154,
    "quote_volume": 272463793.7523,
    "price_change_pct_24h": -0.07,
    "comment": "quiet accumulation box is stable, OBV and CMF confirm money flow, late accumulation watch zone",
    "wyckoff_detail": {
      "prior_decline": 6.49,
      "selling_climax": 10.23,
      "automatic_rally": 15.0,
      "secondary_test": 14.71,
      "spring": 0.0,
      "lps": 20.0
    },
    "status": "WATCH",
    "result_price": null,
    "result_pct": null,
    "result_time": null,
    "time": "2026-05-30 18:03 UTC"
  },
  {
    "id": "SOLUSDT_1780164199",
    "symbol": "SOL/USDT",
    "raw_symbol": "SOLUSDT",
    "timeframe": "1h",
    "direction": "LONG",
    "state": "READY",
    "state_rank": 2,
    "total_score": 58.0,
    "wyckoff_score": 55.51,
    "accumulation_score": 67.68,
    "volume_score": 30.0,
    "obv_cmf_score": 100.0,
    "liquidity_score": 34.25,
    "risk_penalty": 0.0,
    "entry": 83.07,
    "entry_zone": "82.8238 ~ 82.935786",
    "stop_loss": 79.902563,
    "take_profit1": 89.404874,
    "take_profit2": 92.57231,
    "be_target": 87.821155,
    "invalidation": 79.902563,
    "breakout_level": 83.24,
    "sl_pct": -3.81,
    "tp1_pct": 7.63,
    "tp2_pct": 11.44,
    "accum_high": 83.24,
    "accum_low": 80.02,
    "accum_bars": 52,
    "range_pct": 3.92,
    "rvol": 0.02,
    "vol_ratio": 0.02,
    "adx": 24.49,
    "cmf": 0.2615,
    "obv_norm": 0.3646,
    "quote_volume": 96757216.16214,
    "price_change_pct_24h": 0.34,
    "comment": "OBV and CMF confirm money flow, late accumulation watch zone",
    "wyckoff_detail": {
      "prior_decline": 5.71,
      "selling_climax": 14.63,
      "automatic_rally": 15.0,
      "secondary_test": 0.16,
      "spring": 0.0,
      "lps": 20.0
    },
    "status": "WATCH",
    "result_price": null,
    "result_pct": null,
    "result_time": null,
    "time": "2026-05-30 18:03 UTC"
  },
  {
    "id": "DOGEUSDT_1780164201",
    "symbol": "DOGE/USDT",
    "raw_symbol": "DOGEUSDT",
    "timeframe": "1h",
    "direction": "LONG",
    "state": "READY",
    "state_rank": 2,
    "total_score": 50.32,
    "wyckoff_score": 35.52,
    "accumulation_score": 79.29,
    "volume_score": 30.0,
    "obv_cmf_score": 82.5,
    "liquidity_score": 14.67,
    "risk_penalty": 0.0,
    "entry": 0.10153,
    "entry_zone": "0.101321 ~ 0.101354",
    "stop_loss": 0.097286,
    "take_profit1": 0.110018,
    "take_profit2": 0.114262,
    "be_target": 0.107896,
    "invalidation": 0.097286,
    "breakout_level": 0.10183,
    "sl_pct": -4.18,
    "tp1_pct": 8.36,
    "tp2_pct": 12.54,
    "accum_high": 0.10183,
    "accum_low": 0.09744,
    "accum_bars": 28,
    "range_pct": 4.36,
    "rvol": 0.01,
    "vol_ratio": 0.01,
    "adx": 16.36,
    "cmf": 0.2473,
    "obv_norm": 0.1644,
    "quote_volume": 39297357.52467,
    "price_change_pct_24h": 1.12,
    "comment": "quiet accumulation box is stable, OBV and CMF confirm money flow, late accumulation watch zone",
    "wyckoff_detail": {
      "prior_decline": 2.24,
      "selling_climax": 0.0,
      "automatic_rally": 13.27,
      "secondary_test": 0.0,
      "spring": 0.0,
      "lps": 20.0
    },
    "status": "WATCH",
    "result_price": null,
    "result_pct": null,
    "result_time": null,
    "time": "2026-05-30 18:03 UTC"
  },
  {
    "id": "BTCUSDT_1780164197",
    "symbol": "BTC/USDT",
    "raw_symbol": "BTCUSDT",
    "timeframe": "1h",
    "direction": "LONG",
    "state": "READY",
    "state_rank": 2,
    "total_score": 46.97,
    "wyckoff_score": 35.06,
    "accumulation_score": 40.0,
    "volume_score": 23.51,
    "obv_cmf_score": 94.15,
    "liquidity_score": 76.26,
    "risk_penalty": 0.0,
    "entry": 74016.86,
    "entry_zone": "73949.979892 ~ 74075.380095",
    "stop_loss": 72453.969905,
    "take_profit1": 77142.640189,
    "take_profit2": 78705.530284,
    "be_target": 76361.195142,
    "invalidation": 72453.969905,
    "breakout_level": 74775.5,
    "sl_pct": -2.11,
    "tp1_pct": 4.22,
    "tp2_pct": 6.33,
    "accum_high": 74775.5,
    "accum_low": 72512.49,
    "accum_bars": 68,
    "range_pct": 3.07,
    "rvol": 0.0,
    "vol_ratio": 0.0,
    "adx": 25.93,
    "cmf": 0.2467,
    "obv_norm": 0.2214,
    "quote_volume": 668952427.0553906,
    "price_change_pct_24h": 0.05,
    "comment": "OBV and CMF confirm money flow, late accumulation watch zone",
    "wyckoff_detail": {
      "prior_decline": 0.06,
      "selling_climax": 0.0,
      "automatic_rally": 0.0,
      "secondary_test": 15.0,
      "spring": 0.0,
      "lps": 20.0
    },
    "status": "WATCH",
    "result_price": null,
    "result_pct": null,
    "result_time": null,
    "time": "2026-05-30 18:03 UTC"
  },
  {
    "id": "XRPUSDT_1780164199",
    "symbol": "XRP/USDT",
    "raw_symbol": "XRPUSDT",
    "timeframe": "1h",
    "direction": "LONG",
    "state": "READY",
    "state_rank": 2,
    "total_score": 45.3,
    "wyckoff_score": 23.15,
    "accumulation_score": 64.01,
    "volume_score": 30.0,
    "obv_cmf_score": 83.43,
    "liquidity_score": 38.34,
    "risk_penalty": 0.0,
    "entry": 1.3527,
    "entry_zone": "1.350036 ~ 1.355031",
    "stop_loss": 1.308569,
    "take_profit1": 1.440961,
    "take_profit2": 1.485092,
    "be_target": 1.418896,
    "invalidation": 1.308569,
    "breakout_level": 1.3661,
    "sl_pct": -3.26,
    "tp1_pct": 6.52,
    "tp2_pct": 9.79,
    "accum_high": 1.3661,
    "accum_low": 1.3109,
    "accum_bars": 24,
    "range_pct": 4.12,
    "rvol": 0.01,
    "vol_ratio": 0.01,
    "adx": 23.98,
    "cmf": 0.1798,
    "obv_norm": 0.1884,
    "quote_volume": 116799359.02256,
    "price_change_pct_24h": 2.05,
    "comment": "OBV and CMF confirm money flow, late accumulation watch zone",
    "wyckoff_detail": {
      "prior_decline": 0.0,
      "selling_climax": 0.0,
      "automatic_rally": 3.15,
      "secondary_test": 0.0,
      "spring": 0.0,
      "lps": 20.0
    },
    "status": "WATCH",
    "result_price": null,
    "result_pct": null,
    "result_time": null,
    "time": "2026-05-30 18:03 UTC"
  },
  {
    "id": "TRXUSDT_1780164201",
    "symbol": "TRX/USDT",
    "raw_symbol": "TRXUSDT",
    "timeframe": "1h",
    "direction": "LONG",
    "state": "READY",
    "state_rank": 2,
    "total_score": 41.92,
    "wyckoff_score": 37.18,
    "accumulation_score": 40.0,
    "volume_score": 37.08,
    "obv_cmf_score": 78.91,
    "liquidity_score": 15.14,
    "risk_penalty": 0.0,
    "entry": 0.348,
    "entry_zone": "0.34782 ~ 0.348485",
    "stop_loss": 0.339415,
    "take_profit1": 0.365169,
    "take_profit2": 0.373754,
    "be_target": 0.360877,
    "invalidation": 0.339415,
    "breakout_level": 0.3543,
    "sl_pct": -2.47,
    "tp1_pct": 4.93,
    "tp2_pct": 7.4,
    "accum_high": 0.3543,
    "accum_low": 0.3399,
    "accum_bars": 52,
    "range_pct": 4.15,
    "rvol": 0.01,
    "vol_ratio": 0.01,
    "adx": 40.93,
    "cmf": 0.2951,
    "obv_norm": 0.1469,
    "quote_volume": 40155337.52097,
    "price_change_pct_24h": 0.96,
    "comment": "OBV and CMF confirm money flow, late accumulation watch zone",
    "wyckoff_detail": {
      "prior_decline": 5.86,
      "selling_climax": 0.0,
      "automatic_rally": 5.21,
      "secondary_test": 9.87,
      "spring": 0.0,
      "lps": 16.25
    },
    "status": "WATCH",
    "result_price": null,
    "result_pct": null,
    "result_time": null,
    "time": "2026-05-30 18:03 UTC"
  }
]